resources/config-example.yaml
resources/powershell/Open-RlmFirewallPort.ps1
resources/powershell/Restart-RlmService.ps1
resources/systemd/rlm-prometheus.service
rlm_prometheus/__init__.py
rlm_prometheus/cli.py
rlm_prometheus/collector.py
rlm_prometheus/config.py
rlm_prometheus/metrics.py
rlm_prometheus-0.4.0.dist-info/LICENSE
rlm_prometheus-0.4.0.dist-info/METADATA
rlm_prometheus-0.4.0.dist-info/WHEEL
rlm_prometheus-0.4.0.dist-info/entry_points.txt
rlm_prometheus-0.4.0.dist-info/RECORD
