Metadata-Version: 2.1
Name: rlm-prometheus
Version: 0.4.0
Summary: Prometheus metrics collector and exporter for RLM (Reprise License Manager)
Home-page: https://pypi.org/project/rlm-prometheus/
License: GPL-3.0-or-later
Keywords: prometheus,metrics,license-metrics
Author: Niko Ehrenfeuchter
Author-email: nikolaus.ehrenfeuchter@unibas.ch
Requires-Python: >=3.9,<4.0
Classifier: License :: OSI Approved :: GNU General Public License v3 or later (GPLv3+)
Classifier: Programming Language :: Python :: 3
Classifier: Programming Language :: Python :: 3.9
Classifier: Programming Language :: Python :: 3.10
Classifier: Programming Language :: Python :: 3.11
Classifier: Programming Language :: Python :: 3.12
Requires-Dist: PyYAML (>=6.0,<7.0)
Requires-Dist: click (>=8.1.3,<9.0.0)
Requires-Dist: loguru (>=0.6.0,<0.7.0)
Requires-Dist: lxml (>=4.9.1,<5.0.0)
Requires-Dist: numpy (>=1,<2)
Requires-Dist: pandas (>=1.5.1,<2.0.0)
Requires-Dist: prometheus-client (>=0.15.0,<0.16.0)
Requires-Dist: python-box (>=6.1.0,<7.0.0)
Requires-Dist: requests (>=2.28.1,<3.0.0)
Project-URL: Changelog, https://github.com/imcf/rlm-prometheus/blob/main/CHANGELOG.md
Project-URL: Organisation Homepage, https://imcf.one/
Project-URL: Repository, https://github.com/imcf/rlm-prometheus
Project-URL: Twitter, https://twitter.com/imcf_basel
